demes/__init__.py
demes/__main__.py
demes/_version.py
demes/demes.py
demes/load_dump.py
demes/ms.py
demes/py.typed
demes-0.2.2.dist-info/LICENSE
demes-0.2.2.dist-info/METADATA
demes-0.2.2.dist-info/WHEEL
demes-0.2.2.dist-info/entry_points.txt
demes-0.2.2.dist-info/top_level.txt
demes-0.2.2.dist-info/RECORD
