Metadata-Version: 2.1
Name: demes
Version: 0.2.2
Summary: tools for describing demographic models
Home-page: https://github.com/popsim-consortium/demes-python
Author: PopSim Consortium
License: ISC
Project-URL: Documentation, https://popsim-consortium.github.io/demes-docs/
Project-URL: Source Code, https://github.com/popsim-consortium/demes-python/
Project-URL: Bug Tracker, https://github.com/popsim-consortium/demes-python/issues
Platform: UNKNOWN
Classifier: Development Status :: 4 - Beta
Classifier: License :: OSI Approved :: ISC License (ISCL)
Classifier: Operating System :: OS Independent
Classifier: Intended Audience :: Science/Research
Classifier: Programming Language :: Python :: 3
Classifier: Programming Language :: Python :: 3.7
Classifier: Programming Language :: Python :: 3.8
Classifier: Programming Language :: Python :: 3.9
Classifier: Programming Language :: Python :: 3.10
Classifier: Topic :: Scientific/Engineering
Classifier: Topic :: Scientific/Engineering :: Bio-Informatics
Requires-Python: >=3.7
License-File: LICENSE
Requires-Dist: attrs (>=20.3.0)
Requires-Dist: ruamel.yaml (>=0.15.78)
